KeyisBFiles/__init__.py
KeyisBFiles/r.py
KeyisBFiles-1.0.9.dist-info/LICENSE
KeyisBFiles-1.0.9.dist-info/METADATA
KeyisBFiles-1.0.9.dist-info/WHEEL
KeyisBFiles-1.0.9.dist-info/top_level.txt
KeyisBFiles-1.0.9.dist-info/RECORD
