Metadata-Version: 2.1
Name: KeyisBFiles
Version: 1.0.9
Summary: KeyisBFiles
Home-page: https://github.com/KeyisB/libs/tree/main/KeyisBFiles
Author: KeyisB
Author-email: keyisb.pip@gmail.com
License: MMB License v1.0
Classifier: Programming Language :: Python :: 3
Classifier: Operating System :: OS Independent
Requires-Python: >=3.12
License-File: LICENSE
